s3_log_handler/__init__.py
s3_log_handler/handler.py
s3_log_handler-0.1.3.dist-info/LICENSE
s3_log_handler-0.1.3.dist-info/METADATA
s3_log_handler-0.1.3.dist-info/WHEEL
s3_log_handler-0.1.3.dist-info/RECORD
