Metadata-Version: 2.1
Name: s3-log-handler
Version: 0.1.3
Summary: A Python logging handler that uploads logs to Amazon S3
Home-page: https://github.com/yourusername/s3-log-handler
License: MIT
Keywords: logging,s3,aws,handler,async
Author: Your Name
Author-email: your.email@example.com
Requires-Python: >=3.8,<4.0
Classifier: Development Status :: 4 - Beta
Classifier: Intended Audience :: Developers
Classifier: License :: OSI Approved :: MIT License
Classifier: Programming Language :: Python :: 3
Classifier: Programming Language :: Python :: 3.8
Classifier: Programming Language :: Python :: 3.9
Classifier: Programming Language :: Python :: 3.10
Classifier: Programming Language :: Python :: 3.11
Classifier: Programming Language :: Python :: 3.12
Classifier: Programming Language :: Python :: 3.7
Classifier: Topic :: System :: Logging
Requires-Dist: aioboto3 (>=13.2.0,<14.0.0)
Project-URL: Documentation, https://github.com/yourusername/s3-log-handler#readme
Project-URL: Repository, https://github.com/yourusername/s3-log-handler
